[
  {
    "name": "KPMG",
    "coordinates": {
      "lat": 43.4496387,
      "lng": -80.5016019
    },
    "longitude": -80.5016019,
    "latitude": 43.4496387,
    "types": [
      "accounting",
      "finance",
      "point_of_interest",
      "establishment"
    ]
  },
  {
    "name": "DLB Consulting",
    "coordinates": {
      "lat": 43.4442765,
      "lng": -80.4952308
    },
    "longitude": -80.4952308,
    "latitude": 43.4442765,
    "types": [
      "accounting",
      "finance",
      "point_of_interest",
      "establishment"
    ]
  },
  {
    "name": "H&R Block",
    "coordinates": {
      "lat": 43.4364698,
      "lng": -80.5142322
    },
    "longitude": -80.5142322,
    "latitude": 43.4364698,
    "types": [
      "accounting",
      "finance",
      "point_of_interest",
      "establishment"
    ]
  },
  {
    "name": "Comp-A-Counting Services",
    "coordinates": {
      "lat": 43.4520208,
      "lng": -80.4806236
    },
    "longitude": -80.4806236,
    "latitude": 43.4520208,
    "types": [
      "accounting",
      "finance",
      "point_of_interest",
      "establishment"
    ]
  },
  {
    "name": "Zebroski And Associates",
    "coordinates": {
      "lat": 43.49381899999999,
      "lng": -80.53633660000001
    },
    "longitude": -80.53633660000001,
    "latitude": 43.49381899999999,
    "types": [
      "accounting",
      "finance",
      "point_of_interest",
      "establishment"
    ]
  },
  {
    "name": "Doane Grant Thornton LLP",
    "coordinates": {
      "lat": 43.5081514,
      "lng": -80.5395649
    },
    "longitude": -80.5395649,
    "latitude": 43.5081514,
    "types": [
      "accounting",
      "finance",
      "point_of_interest",
      "establishment"
    ]
  },
  {
    "name": "BELL Chartered Accountants",
    "coordinates": {
      "lat": 43.47445459999999,
      "lng": -80.5935077
    },
    "longitude": -80.5935077,
    "latitude": 43.47445459999999,
    "types": [
      "accounting",
      "finance",
      "point_of_interest",
      "establishment"
    ]
  },
  {
    "name": "Vine & Partners LLP",
    "coordinates": {
      "lat": 43.46312870000001,
      "lng": -80.4657099
    },
    "longitude": -80.4657099,
    "latitude": 43.46312870000001,
    "types": [
      "accounting",
      "finance",
      "point_of_interest",
      "establishment"
    ]
  },
  {
    "name": "LRK Tax LLP",
    "coordinates": {
      "lat": 43.4752034,
      "lng": -80.47862409999999
    },
    "longitude": -80.47862409999999,
    "latitude": 43.4752034,
    "types": [
      "accounting",
      "finance",
      "point_of_interest",
      "establishment"
    ]
  },
  {
    "name": "Toffson Management",
    "coordinates": {
      "lat": 43.453074,
      "lng": -80.5173969
    },
    "longitude": -80.5173969,
    "latitude": 43.453074,
    "types": [
      "accounting",
      "finance",
      "point_of_interest",
      "establishment"
    ]
  },
  {
    "name": "Tax Care Inc",
    "coordinates": {
      "lat": 43.4858027,
      "lng": -80.5286593
    },
    "longitude": -80.5286593,
    "latitude": 43.4858027,
    "types": [
      "accounting",
      "finance",
      "point_of_interest",
      "establishment"
    ]
  },
  {
    "name": "Ark Accounting & Tax Professional Corporation",
    "coordinates": {
      "lat": 43.4513531,
      "lng": -80.4713419
    },
    "longitude": -80.4713419,
    "latitude": 43.4513531,
    "types": [
      "accounting",
      "finance",
      "point_of_interest",
      "establishment"
    ]
  },
  {
    "name": "Thornegate Consulting",
    "coordinates": {
      "lat": 43.4995333,
      "lng": -80.50036039999999
    },
    "longitude": -80.50036039999999,
    "latitude": 43.4995333,
    "types": [
      "accounting",
      "finance",
      "point_of_interest",
      "establishment"
    ]
  },
  {
    "name": "Books By Kristi",
    "coordinates": {
      "lat": 43.4791064,
      "lng": -80.5162405
    },
    "longitude": -80.5162405,
    "latitude": 43.4791064,
    "types": [
      "accounting",
      "finance",
      "point_of_interest",
      "establishment"
    ]
  },
  {
    "name": "Eggett Tax Services",
    "coordinates": {
      "lat": 43.4444082,
      "lng": -80.47761179999999
    },
    "longitude": -80.47761179999999,
    "latitude": 43.4444082,
    "types": [
      "accounting",
      "finance",
      "point_of_interest",
      "establishment"
    ]
  },
  {
    "name": "GE Solutions",
    "coordinates": {
      "lat": 43.4614846,
      "lng": -80.45309929999999
    },
    "longitude": -80.45309929999999,
    "latitude": 43.4614846,
    "types": [
      "accounting",
      "finance",
      "point_of_interest",
      "establishment"
    ]
  },
  {
    "name": "Lund & Associates",
    "coordinates": {
      "lat": 43.4412186,
      "lng": -80.4703921
    },
    "longitude": -80.4703921,
    "latitude": 43.4412186,
    "types": [
      "accounting",
      "finance",
      "point_of_interest",
      "establishment"
    ]
  },
  {
    "name": "Accounting 911",
    "coordinates": {
      "lat": 43.4148157,
      "lng": -80.4822966
    },
    "longitude": -80.4822966,
    "latitude": 43.4148157,
    "types": [
      "accounting",
      "finance",
      "point_of_interest",
      "establishment"
    ]
  },
  {
    "name": "CK Accounting & Tax Services",
    "coordinates": {
      "lat": 43.4125236,
      "lng": -80.5365977
    },
    "longitude": -80.5365977,
    "latitude": 43.4125236,
    "types": [
      "accounting",
      "finance",
      "point_of_interest",
      "establishment"
    ]
  },
  {
    "name": "Dynac Inc",
    "coordinates": {
      "lat": 43.4509118,
      "lng": -80.5135779
    },
    "longitude": -80.5135779,
    "latitude": 43.4509118,
    "types": [
      "accounting",
      "finance",
      "point_of_interest",
      "establishment"
    ]
  },
  {
    "name": "The Prudent Accounting and Tax Services",
    "coordinates": {
      "lat": 43.4531614,
      "lng": -80.5175223
    },
    "longitude": -80.5175223,
    "latitude": 43.4531614,
    "types": [
      "accounting",
      "finance",
      "point_of_interest",
      "establishment"
    ]
  },
  {
    "name": "Fritsch & Laitar",
    "coordinates": {
      "lat": 43.4888511,
      "lng": -80.494215
    },
    "longitude": -80.494215,
    "latitude": 43.4888511,
    "types": [
      "accounting",
      "finance",
      "point_of_interest",
      "establishment"
    ]
  },
  {
    "name": "H&R Block",
    "coordinates": {
      "lat": 43.4250487,
      "lng": -80.55406599999999
    },
    "longitude": -80.55406599999999,
    "latitude": 43.4250487,
    "types": [
      "accounting",
      "finance",
      "point_of_interest",
      "establishment"
    ]
  },
  {
    "name": "Cameron Keller & Company",
    "coordinates": {
      "lat": 43.4939319,
      "lng": -80.5373221
    },
    "longitude": -80.5373221,
    "latitude": 43.4939319,
    "types": [
      "accounting",
      "finance",
      "point_of_interest",
      "establishment"
    ]
  },
  {
    "name": "Sathya Tax Plus Inc.",
    "coordinates": {
      "lat": 43.4317779,
      "lng": -80.50914379999999
    },
    "longitude": -80.50914379999999,
    "latitude": 43.4317779,
    "types": [
      "accounting",
      "finance",
      "point_of_interest",
      "establishment"
    ]
  },
  {
    "name": "Cash-A-Cheque",
    "coordinates": {
      "lat": 43.4363086,
      "lng": -80.51417169999999
    },
    "longitude": -80.51417169999999,
    "latitude": 43.4363086,
    "types": [
      "accounting",
      "finance",
      "point_of_interest",
      "establishment"
    ]
  },
  {
    "name": "Common Cents Accounting Services",
    "coordinates": {
      "lat": 43.4447833,
      "lng": -80.4777146
    },
    "longitude": -80.4777146,
    "latitude": 43.4447833,
    "types": [
      "accounting",
      "finance",
      "point_of_interest",
      "establishment"
    ]
  },
  {
    "name": "Arbuckle Financial Services",
    "coordinates": {
      "lat": 43.4664763,
      "lng": -80.5208042
    },
    "longitude": -80.5208042,
    "latitude": 43.4664763,
    "types": [
      "accounting",
      "finance",
      "point_of_interest",
      "establishment"
    ]
  },
  {
    "name": "McKerlie Michael J, CPA Professional Corporation",
    "coordinates": {
      "lat": 43.4802107,
      "lng": -80.5226789
    },
    "longitude": -80.5226789,
    "latitude": 43.4802107,
    "types": [
      "accounting",
      "finance",
      "point_of_interest",
      "establishment"
    ]
  },
  {
    "name": "Mitchell & Company",
    "coordinates": {
      "lat": 43.4477376,
      "lng": -80.4778134
    },
    "longitude": -80.4778134,
    "latitude": 43.4477376,
    "types": [
      "accounting",
      "finance",
      "point_of_interest",
      "establishment"
    ]
  },
  {
    "name": "Ledgers (Kitchener)",
    "coordinates": {
      "lat": 43.45448270000001,
      "lng": -80.51902009999999
    },
    "longitude": -80.51902009999999,
    "latitude": 43.45448270000001,
    "types": [
      "accounting",
      "finance",
      "local_government_office",
      "point_of_interest",
      "establishment"
    ]
  },
  {
    "name": "Acumax Business Solutions Inc",
    "coordinates": {
      "lat": 43.4889101,
      "lng": -80.49413179999999
    },
    "longitude": -80.49413179999999,
    "latitude": 43.4889101,
    "types": [
      "accounting",
      "finance",
      "point_of_interest",
      "establishment"
    ]
  },
  {
    "name": "sss",
    "coordinates": {
      "lat": 43.46991149999999,
      "lng": -80.5236389
    },
    "longitude": -80.5236389,
    "latitude": 43.46991149999999,
    "types": [
      "accounting",
      "finance",
      "point_of_interest",
      "establishment"
    ]
  },
  {
    "name": "Tom Wilhelm Professional Corporation",
    "coordinates": {
      "lat": 43.45128270000001,
      "lng": -80.4840476
    },
    "longitude": -80.4840476,
    "latitude": 43.45128270000001,
    "types": [
      "accounting",
      "finance",
      "point_of_interest",
      "establishment"
    ]
  },
  {
    "name": "Larry Stolberg CPA | Waterloo Tax Specialist",
    "coordinates": {
      "lat": 43.4646993,
      "lng": -80.5219499
    },
    "longitude": -80.5219499,
    "latitude": 43.4646993,
    "types": [
      "accounting",
      "finance",
      "point_of_interest",
      "establishment"
    ]
  },
  {
    "name": "Edward Jones - Financial Advisor",
    "coordinates": {
      "lat": 43.4606528,
      "lng": -80.5193951
    },
    "longitude": -80.5193951,
    "latitude": 43.4606528,
    "types": [
      "accounting",
      "finance",
      "point_of_interest",
      "establishment"
    ]
  },
  {
    "name": "Sheila Matson, CPA, CA",
    "coordinates": {
      "lat": 43.4564447,
      "lng": -80.5319286
    },
    "longitude": -80.5319286,
    "latitude": 43.4564447,
    "types": [
      "accounting",
      "finance",
      "point_of_interest",
      "establishment"
    ]
  },
  {
    "name": "Spruce Accounting Professional Corporation",
    "coordinates": {
      "lat": 43.4790947,
      "lng": -80.5264504
    },
    "longitude": -80.5264504,
    "latitude": 43.4790947,
    "types": [
      "accounting",
      "finance",
      "point_of_interest",
      "establishment"
    ]
  },
  {
    "name": "AccountingKW",
    "coordinates": {
      "lat": 43.4633148,
      "lng": -80.4881699
    },
    "longitude": -80.4881699,
    "latitude": 43.4633148,
    "types": [
      "accounting",
      "finance",
      "point_of_interest",
      "establishment"
    ]
  },
  {
    "name": "Simply Bookkeeping",
    "coordinates": {
      "lat": 43.4516395,
      "lng": -80.4925337
    },
    "longitude": -80.4925337,
    "latitude": 43.4516395,
    "types": [
      "accounting",
      "finance",
      "point_of_interest",
      "establishment"
    ]
  },
  {
    "name": "Dan Bechtold Ca",
    "coordinates": {
      "lat": 43.4442762,
      "lng": -80.495183
    },
    "longitude": -80.495183,
    "latitude": 43.4442762,
    "types": [
      "accounting",
      "finance",
      "point_of_interest",
      "establishment"
    ]
  },
  {
    "name": "Dedicated Bookkeeping Solutions Inc.",
    "coordinates": {
      "lat": 43.44520899999999,
      "lng": -80.49284349999999
    },
    "longitude": -80.49284349999999,
    "latitude": 43.44520899999999,
    "types": [
      "accounting",
      "finance",
      "point_of_interest",
      "establishment"
    ]
  },
  {
    "name": "Deborah Hughes, CPA",
    "coordinates": {
      "lat": 43.44520899999999,
      "lng": -80.49284349999999
    },
    "longitude": -80.49284349999999,
    "latitude": 43.44520899999999,
    "types": [
      "accounting",
      "finance",
      "point_of_interest",
      "establishment"
    ]
  },
  {
    "name": "MAC LLP",
    "coordinates": {
      "lat": 43.4923449,
      "lng": -80.53825909999999
    },
    "longitude": -80.53825909999999,
    "latitude": 43.4923449,
    "types": [
      "accounting",
      "finance",
      "point_of_interest",
      "establishment"
    ]
  },
  {
    "name": "Dallmeier Accounting Professional Corporation",
    "coordinates": {
      "lat": 43.4773479,
      "lng": -80.48160279999999
    },
    "longitude": -80.48160279999999,
    "latitude": 43.4773479,
    "types": [
      "accounting",
      "finance",
      "point_of_interest",
      "establishment"
    ]
  },
  {
    "name": "RLB LLP - Kitchener Office",
    "coordinates": {
      "lat": 43.4773933,
      "lng": -80.48161800000001
    },
    "longitude": -80.48161800000001,
    "latitude": 43.4773933,
    "types": [
      "accounting",
      "finance",
      "point_of_interest",
      "establishment"
    ]
  },
  {
    "name": "Brixton, Thomas & Ahmad LLP",
    "coordinates": {
      "lat": 43.4554897,
      "lng": -80.4789227
    },
    "longitude": -80.4789227,
    "latitude": 43.4554897,
    "types": [
      "accounting",
      "finance",
      "point_of_interest",
      "establishment"
    ]
  },
  {
    "name": "Argyle Bookkeeping Services Inc.,",
    "coordinates": {
      "lat": 43.4751428,
      "lng": -80.4787341
    },
    "longitude": -80.4787341,
    "latitude": 43.4751428,
    "types": [
      "accounting",
      "finance",
      "point_of_interest",
      "establishment"
    ]
  },
  {
    "name": "H&R Block",
    "coordinates": {
      "lat": 43.4979436,
      "lng": -80.52682829999999
    },
    "longitude": -80.52682829999999,
    "latitude": 43.4979436,
    "types": [
      "accounting",
      "finance",
      "point_of_interest",
      "establishment"
    ]
  },
  {
    "name": "Start To Finish Bookkeeping Services",
    "coordinates": {
      "lat": 43.4932754,
      "lng": -80.5479666
    },
    "longitude": -80.5479666,
    "latitude": 43.4932754,
    "types": [
      "accounting",
      "finance",
      "point_of_interest",
      "establishment"
    ]
  },
  {
    "name": "MNP LLP - Accounting, Business Consulting and Tax Services",
    "coordinates": {
      "lat": 43.49751699999999,
      "lng": -80.544061
    },
    "longitude": -80.544061,
    "latitude": 43.49751699999999,
    "types": [
      "accounting",
      "finance",
      "point_of_interest",
      "establishment"
    ]
  },
  {
    "name": "Baker Tilly Canada Cooperative (formerly Collins Barrow National Cooperative Incorporated)",
    "coordinates": {
      "lat": 43.49737509999999,
      "lng": -80.54723129999999
    },
    "longitude": -80.54723129999999,
    "latitude": 43.49737509999999,
    "types": [
      "accounting",
      "finance",
      "point_of_interest",
      "establishment"
    ]
  },
  {
    "name": "AC Cloud Inc.",
    "coordinates": {
      "lat": 43.5030496,
      "lng": -80.5276804
    },
    "longitude": -80.5276804,
    "latitude": 43.5030496,
    "types": [
      "accounting",
      "finance",
      "point_of_interest",
      "establishment"
    ]
  },
  {
    "name": "Prestige Home Inspection Service",
    "coordinates": {
      "lat": 43.4112253,
      "lng": -80.4733254
    },
    "longitude": -80.4733254,
    "latitude": 43.4112253,
    "types": [
      "roofing_contractor",
      "accounting",
      "finance",
      "point_of_interest",
      "establishment"
    ]
  },
  {
    "name": "Gary J Martin Professional Corporation",
    "coordinates": {
      "lat": 43.43978560000001,
      "lng": -80.465349
    },
    "longitude": -80.465349,
    "latitude": 43.43978560000001,
    "types": [
      "accounting",
      "finance",
      "point_of_interest",
      "establishment"
    ]
  },
  {
    "name": "Ironbooks Inc.",
    "coordinates": {
      "lat": 43.5124628,
      "lng": -80.5287987
    },
    "longitude": -80.5287987,
    "latitude": 43.5124628,
    "types": [
      "accounting",
      "finance",
      "point_of_interest",
      "establishment"
    ]
  },
  {
    "name": "Advantage Accounting",
    "coordinates": {
      "lat": 43.4249393,
      "lng": -80.47422790000002
    },
    "longitude": -80.47422790000002,
    "latitude": 43.4249393,
    "types": [
      "accounting",
      "local_government_office",
      "finance",
      "point_of_interest",
      "establishment"
    ]
  },
  {
    "name": "Scott Nosal Professional Corporation",
    "coordinates": {
      "lat": 43.50929629999999,
      "lng": -80.46184939999999
    },
    "longitude": -80.46184939999999,
    "latitude": 43.50929629999999,
    "types": [
      "accounting",
      "finance",
      "point_of_interest",
      "establishment"
    ]
  },
  {
    "name": "Informative Tax Inc",
    "coordinates": {
      "lat": 43.40719759999999,
      "lng": -80.5024257
    },
    "longitude": -80.5024257,
    "latitude": 43.40719759999999,
    "types": [
      "accounting",
      "finance",
      "point_of_interest",
      "establishment"
    ]
  },
  {
    "name": "H&R Block",
    "coordinates": {
      "lat": 43.42391490000001,
      "lng": -80.4404318
    },
    "longitude": -80.4404318,
    "latitude": 43.42391490000001,
    "types": [
      "accounting",
      "finance",
      "point_of_interest",
      "establishment"
    ]
  }
]